{
  "phase": "Phase F.5",
  "edge_count": 87,
  "relationships": {
    "SUPPORTED_BY": [
      {
        "from": "B1",
        "to": "B14",
        "relationship": "SUPPORTED_BY",
        "confidence": 0.93,
        "end": "start"
      },
      {
        "from": "B2",
        "to": "WALL_74",
        "relationship": "SUPPORTED_BY",
        "confidence": 0.94,
        "end": "start"
      },
      {
        "from": "B3",
        "to": "WALL_79",
        "relationship": "SUPPORTED_BY",
        "confidence": 0.94,
        "end": "start"
      },
      {
        "from": "B4",
        "to": "B13",
        "relationship": "SUPPORTED_BY",
        "confidence": 0.93,
        "end": "start"
      },
      {
        "from": "B4",
        "to": "B12",
        "relationship": "SUPPORTED_BY",
        "confidence": 0.93,
        "end": "end"
      },
      {
        "from": "B5",
        "to": "B13",
        "relationship": "SUPPORTED_BY",
        "confidence": 0.93,
        "end": "start"
      },
      {
        "from": "B5",
        "to": "B12",
        "relationship": "SUPPORTED_BY",
        "confidence": 0.93,
        "end": "end"
      },
      {
        "from": "B6",
        "to": "COLUMN_5",
        "relationship": "SUPPORTED_BY",
        "confidence": 0.97,
        "end": "start"
      },
      {
        "from": "B6",
        "to": "WALL_77",
        "relationship": "SUPPORTED_BY",
        "confidence": 0.94,
        "end": "end"
      },
      {
        "from": "B7",
        "to": "WALL_77",
        "relationship": "SUPPORTED_BY",
        "confidence": 0.94,
        "end": "start"
      },
      {
        "from": "B8",
        "to": "WALL_29",
        "relationship": "SUPPORTED_BY",
        "confidence": 0.94,
        "end": "start"
      },
      {
        "from": "B8",
        "to": "WALL_36",
        "relationship": "SUPPORTED_BY",
        "confidence": 0.94,
        "end": "end"
      },
      {
        "from": "B9",
        "to": "COLUMN_4",
        "relationship": "SUPPORTED_BY",
        "confidence": 0.97,
        "end": "start"
      },
      {
        "from": "B10",
        "to": "B11",
        "relationship": "SUPPORTED_BY",
        "confidence": 0.93,
        "end": "start"
      },
      {
        "from": "B11",
        "to": "B10",
        "relationship": "SUPPORTED_BY",
        "confidence": 0.93,
        "end": "start"
      },
      {
        "from": "B11",
        "to": "WALL_45",
        "relationship": "SUPPORTED_BY",
        "confidence": 0.94,
        "end": "end"
      },
      {
        "from": "B12",
        "to": "B4",
        "relationship": "SUPPORTED_BY",
        "confidence": 0.93,
        "end": "start"
      },
      {
        "from": "B12",
        "to": "B5",
        "relationship": "SUPPORTED_BY",
        "confidence": 0.93,
        "end": "end"
      },
      {
        "from": "B13",
        "to": "B4",
        "relationship": "SUPPORTED_BY",
        "confidence": 0.93,
        "end": "start"
      },
      {
        "from": "B13",
        "to": "B5",
        "relationship": "SUPPORTED_BY",
        "confidence": 0.93,
        "end": "end"
      },
      {
        "from": "B14",
        "to": "WALL_43",
        "relationship": "SUPPORTED_BY",
        "confidence": 0.94,
        "end": "start"
      },
      {
        "from": "B14",
        "to": "WALL_34",
        "relationship": "SUPPORTED_BY",
        "confidence": 0.94,
        "end": "end"
      },
      {
        "from": "B15",
        "to": "WALL_74",
        "relationship": "SUPPORTED_BY",
        "confidence": 0.94,
        "end": "start"
      },
      {
        "from": "B15",
        "to": "WALL_77",
        "relationship": "SUPPORTED_BY",
        "confidence": 0.94,
        "end": "end"
      },
      {
        "from": "B16",
        "to": "WALL_58",
        "relationship": "SUPPORTED_BY",
        "confidence": 0.94,
        "end": "start"
      },
      {
        "from": "B16",
        "to": "WALL_50",
        "relationship": "SUPPORTED_BY",
        "confidence": 0.94,
        "end": "end"
      },
      {
        "from": "B17",
        "to": "WALL_79",
        "relationship": "SUPPORTED_BY",
        "confidence": 0.94,
        "end": "start"
      },
      {
        "from": "B17",
        "to": "WALL_47",
        "relationship": "SUPPORTED_BY",
        "confidence": 0.94,
        "end": "end"
      },
      {
        "from": "B18",
        "to": "WALL_79",
        "relationship": "SUPPORTED_BY",
        "confidence": 0.94,
        "end": "start"
      },
      {
        "from": "B18",
        "to": "WALL_77",
        "relationship": "SUPPORTED_BY",
        "confidence": 0.94,
        "end": "end"
      }
    ],
    "CONNECTED_TO": [
      {
        "from": "B1",
        "to": "B14",
        "relationship": "CONNECTED_TO",
        "confidence": 0.93
      },
      {
        "from": "B2",
        "to": "WALL_74",
        "relationship": "CONNECTED_TO",
        "confidence": 0.94
      },
      {
        "from": "B3",
        "to": "WALL_79",
        "relationship": "CONNECTED_TO",
        "confidence": 0.94
      },
      {
        "from": "B4",
        "to": "B13",
        "relationship": "CONNECTED_TO",
        "confidence": 0.93
      },
      {
        "from": "B4",
        "to": "B12",
        "relationship": "CONNECTED_TO",
        "confidence": 0.93
      },
      {
        "from": "B5",
        "to": "B13",
        "relationship": "CONNECTED_TO",
        "confidence": 0.93
      },
      {
        "from": "B5",
        "to": "B12",
        "relationship": "CONNECTED_TO",
        "confidence": 0.93
      },
      {
        "from": "B6",
        "to": "COLUMN_5",
        "relationship": "CONNECTED_TO",
        "confidence": 0.97
      },
      {
        "from": "B6",
        "to": "WALL_77",
        "relationship": "CONNECTED_TO",
        "confidence": 0.94
      },
      {
        "from": "B7",
        "to": "WALL_77",
        "relationship": "CONNECTED_TO",
        "confidence": 0.94
      },
      {
        "from": "B8",
        "to": "WALL_29",
        "relationship": "CONNECTED_TO",
        "confidence": 0.94
      },
      {
        "from": "B8",
        "to": "WALL_36",
        "relationship": "CONNECTED_TO",
        "confidence": 0.94
      },
      {
        "from": "B9",
        "to": "COLUMN_4",
        "relationship": "CONNECTED_TO",
        "confidence": 0.97
      },
      {
        "from": "B10",
        "to": "B11",
        "relationship": "CONNECTED_TO",
        "confidence": 0.93
      },
      {
        "from": "B11",
        "to": "B10",
        "relationship": "CONNECTED_TO",
        "confidence": 0.93
      },
      {
        "from": "B11",
        "to": "WALL_45",
        "relationship": "CONNECTED_TO",
        "confidence": 0.94
      },
      {
        "from": "B12",
        "to": "B4",
        "relationship": "CONNECTED_TO",
        "confidence": 0.93
      },
      {
        "from": "B12",
        "to": "B5",
        "relationship": "CONNECTED_TO",
        "confidence": 0.93
      },
      {
        "from": "B13",
        "to": "B4",
        "relationship": "CONNECTED_TO",
        "confidence": 0.93
      },
      {
        "from": "B13",
        "to": "B5",
        "relationship": "CONNECTED_TO",
        "confidence": 0.93
      },
      {
        "from": "B14",
        "to": "WALL_43",
        "relationship": "CONNECTED_TO",
        "confidence": 0.94
      },
      {
        "from": "B14",
        "to": "WALL_34",
        "relationship": "CONNECTED_TO",
        "confidence": 0.94
      },
      {
        "from": "B15",
        "to": "WALL_74",
        "relationship": "CONNECTED_TO",
        "confidence": 0.94
      },
      {
        "from": "B15",
        "to": "WALL_77",
        "relationship": "CONNECTED_TO",
        "confidence": 0.94
      },
      {
        "from": "B16",
        "to": "WALL_58",
        "relationship": "CONNECTED_TO",
        "confidence": 0.94
      },
      {
        "from": "B16",
        "to": "WALL_50",
        "relationship": "CONNECTED_TO",
        "confidence": 0.94
      },
      {
        "from": "B17",
        "to": "WALL_79",
        "relationship": "CONNECTED_TO",
        "confidence": 0.94
      },
      {
        "from": "B17",
        "to": "WALL_47",
        "relationship": "CONNECTED_TO",
        "confidence": 0.94
      },
      {
        "from": "B18",
        "to": "WALL_79",
        "relationship": "CONNECTED_TO",
        "confidence": 0.94
      },
      {
        "from": "B18",
        "to": "WALL_77",
        "relationship": "CONNECTED_TO",
        "confidence": 0.94
      }
    ],
    "CONTINUOUS_WITH": [
      {
        "from": "B4",
        "to": "B5",
        "relationship": "CONTINUOUS_WITH",
        "confidence": 0.88,
        "via_support": "B12"
      },
      {
        "from": "B12",
        "to": "B13",
        "relationship": "CONTINUOUS_WITH",
        "confidence": 0.88,
        "via_support": "B4"
      },
      {
        "from": "B2",
        "to": "B15",
        "relationship": "CONTINUOUS_WITH",
        "confidence": 0.88,
        "via_support": "WALL_74"
      },
      {
        "from": "B6",
        "to": "B7",
        "relationship": "CONTINUOUS_WITH",
        "confidence": 0.88,
        "via_support": "WALL_77"
      },
      {
        "from": "B6",
        "to": "B15",
        "relationship": "CONTINUOUS_WITH",
        "confidence": 0.88,
        "via_support": "WALL_77"
      },
      {
        "from": "B6",
        "to": "B18",
        "relationship": "CONTINUOUS_WITH",
        "confidence": 0.88,
        "via_support": "WALL_77"
      },
      {
        "from": "B7",
        "to": "B15",
        "relationship": "CONTINUOUS_WITH",
        "confidence": 0.88,
        "via_support": "WALL_77"
      },
      {
        "from": "B7",
        "to": "B18",
        "relationship": "CONTINUOUS_WITH",
        "confidence": 0.88,
        "via_support": "WALL_77"
      },
      {
        "from": "B15",
        "to": "B18",
        "relationship": "CONTINUOUS_WITH",
        "confidence": 0.88,
        "via_support": "WALL_77"
      },
      {
        "from": "B3",
        "to": "B17",
        "relationship": "CONTINUOUS_WITH",
        "confidence": 0.88,
        "via_support": "WALL_79"
      },
      {
        "from": "B3",
        "to": "B18",
        "relationship": "CONTINUOUS_WITH",
        "confidence": 0.88,
        "via_support": "WALL_79"
      },
      {
        "from": "B17",
        "to": "B18",
        "relationship": "CONTINUOUS_WITH",
        "confidence": 0.88,
        "via_support": "WALL_79"
      },
      {
        "from": "B4",
        "to": "B13",
        "relationship": "CONTINUOUS_WITH",
        "confidence": 0.93,
        "joint_end": "left"
      },
      {
        "from": "B4",
        "to": "B12",
        "relationship": "CONTINUOUS_WITH",
        "confidence": 0.93,
        "joint_end": "right"
      },
      {
        "from": "B5",
        "to": "B13",
        "relationship": "CONTINUOUS_WITH",
        "confidence": 0.93,
        "joint_end": "left"
      },
      {
        "from": "B5",
        "to": "B12",
        "relationship": "CONTINUOUS_WITH",
        "confidence": 0.93,
        "joint_end": "right"
      }
    ],
    "INTERSECTS": [
      {
        "from": "B2",
        "to": "B15",
        "relationship": "INTERSECTS",
        "confidence": 0.9991,
        "distance_mm": 0.218
      },
      {
        "from": "B3",
        "to": "B17",
        "relationship": "INTERSECTS",
        "confidence": 1.0,
        "distance_mm": 0.0
      },
      {
        "from": "B3",
        "to": "B18",
        "relationship": "INTERSECTS",
        "confidence": 1.0,
        "distance_mm": 0.0
      },
      {
        "from": "B4",
        "to": "B13",
        "relationship": "INTERSECTS",
        "confidence": 0.7,
        "distance_mm": 200.0
      },
      {
        "from": "B5",
        "to": "B13",
        "relationship": "INTERSECTS",
        "confidence": 1.0,
        "distance_mm": 0.0
      },
      {
        "from": "B5",
        "to": "B12",
        "relationship": "INTERSECTS",
        "confidence": 0.7,
        "distance_mm": 200.0
      },
      {
        "from": "B6",
        "to": "B7",
        "relationship": "INTERSECTS",
        "confidence": 0.7,
        "distance_mm": 200.0
      },
      {
        "from": "B6",
        "to": "B15",
        "relationship": "INTERSECTS",
        "confidence": 0.9797,
        "distance_mm": 5.073
      },
      {
        "from": "B7",
        "to": "B15",
        "relationship": "INTERSECTS",
        "confidence": 0.7,
        "distance_mm": 200.062
      },
      {
        "from": "B7",
        "to": "B18",
        "relationship": "INTERSECTS",
        "confidence": 1.0,
        "distance_mm": 0.0
      },
      {
        "from": "B10",
        "to": "B11",
        "relationship": "INTERSECTS",
        "confidence": 0.7,
        "distance_mm": 200.031
      }
    ]
  },
  "edges": [
    {
      "from": "BEAM::B1",
      "to": "BEAM::B14",
      "relationship": "SUPPORTED_BY",
      "confidence": 0.93,
      "end": "start",
      "legacy_from": "B1",
      "legacy_to": "B14"
    },
    {
      "from": "BEAM::B1",
      "to": "BEAM::B14",
      "relationship": "CONNECTED_TO",
      "confidence": 0.93,
      "legacy_from": "B1",
      "legacy_to": "B14"
    },
    {
      "from": "BEAM::B2",
      "to": "WALL::74",
      "relationship": "SUPPORTED_BY",
      "confidence": 0.94,
      "end": "start",
      "legacy_from": "B2",
      "legacy_to": "WALL_74"
    },
    {
      "from": "BEAM::B2",
      "to": "WALL::74",
      "relationship": "CONNECTED_TO",
      "confidence": 0.94,
      "legacy_from": "B2",
      "legacy_to": "WALL_74"
    },
    {
      "from": "BEAM::B3",
      "to": "WALL::79",
      "relationship": "SUPPORTED_BY",
      "confidence": 0.94,
      "end": "start",
      "legacy_from": "B3",
      "legacy_to": "WALL_79"
    },
    {
      "from": "BEAM::B3",
      "to": "WALL::79",
      "relationship": "CONNECTED_TO",
      "confidence": 0.94,
      "legacy_from": "B3",
      "legacy_to": "WALL_79"
    },
    {
      "from": "BEAM::B4",
      "to": "BEAM::B13",
      "relationship": "SUPPORTED_BY",
      "confidence": 0.93,
      "end": "start",
      "legacy_from": "B4",
      "legacy_to": "B13"
    },
    {
      "from": "BEAM::B4",
      "to": "BEAM::B13",
      "relationship": "CONNECTED_TO",
      "confidence": 0.93,
      "legacy_from": "B4",
      "legacy_to": "B13"
    },
    {
      "from": "BEAM::B4",
      "to": "BEAM::B12",
      "relationship": "SUPPORTED_BY",
      "confidence": 0.93,
      "end": "end",
      "legacy_from": "B4",
      "legacy_to": "B12"
    },
    {
      "from": "BEAM::B4",
      "to": "BEAM::B12",
      "relationship": "CONNECTED_TO",
      "confidence": 0.93,
      "legacy_from": "B4",
      "legacy_to": "B12"
    },
    {
      "from": "BEAM::B5",
      "to": "BEAM::B13",
      "relationship": "SUPPORTED_BY",
      "confidence": 0.93,
      "end": "start",
      "legacy_from": "B5",
      "legacy_to": "B13"
    },
    {
      "from": "BEAM::B5",
      "to": "BEAM::B13",
      "relationship": "CONNECTED_TO",
      "confidence": 0.93,
      "legacy_from": "B5",
      "legacy_to": "B13"
    },
    {
      "from": "BEAM::B5",
      "to": "BEAM::B12",
      "relationship": "SUPPORTED_BY",
      "confidence": 0.93,
      "end": "end",
      "legacy_from": "B5",
      "legacy_to": "B12"
    },
    {
      "from": "BEAM::B5",
      "to": "BEAM::B12",
      "relationship": "CONNECTED_TO",
      "confidence": 0.93,
      "legacy_from": "B5",
      "legacy_to": "B12"
    },
    {
      "from": "BEAM::B6",
      "to": "COLUMN::5",
      "relationship": "SUPPORTED_BY",
      "confidence": 0.97,
      "end": "start",
      "legacy_from": "B6",
      "legacy_to": "COLUMN_5"
    },
    {
      "from": "BEAM::B6",
      "to": "COLUMN::5",
      "relationship": "CONNECTED_TO",
      "confidence": 0.97,
      "legacy_from": "B6",
      "legacy_to": "COLUMN_5"
    },
    {
      "from": "BEAM::B6",
      "to": "WALL::77",
      "relationship": "SUPPORTED_BY",
      "confidence": 0.94,
      "end": "end",
      "legacy_from": "B6",
      "legacy_to": "WALL_77"
    },
    {
      "from": "BEAM::B6",
      "to": "WALL::77",
      "relationship": "CONNECTED_TO",
      "confidence": 0.94,
      "legacy_from": "B6",
      "legacy_to": "WALL_77"
    },
    {
      "from": "BEAM::B7",
      "to": "WALL::77",
      "relationship": "SUPPORTED_BY",
      "confidence": 0.94,
      "end": "start",
      "legacy_from": "B7",
      "legacy_to": "WALL_77"
    },
    {
      "from": "BEAM::B7",
      "to": "WALL::77",
      "relationship": "CONNECTED_TO",
      "confidence": 0.94,
      "legacy_from": "B7",
      "legacy_to": "WALL_77"
    },
    {
      "from": "BEAM::B8",
      "to": "WALL::29",
      "relationship": "SUPPORTED_BY",
      "confidence": 0.94,
      "end": "start",
      "legacy_from": "B8",
      "legacy_to": "WALL_29"
    },
    {
      "from": "BEAM::B8",
      "to": "WALL::29",
      "relationship": "CONNECTED_TO",
      "confidence": 0.94,
      "legacy_from": "B8",
      "legacy_to": "WALL_29"
    },
    {
      "from": "BEAM::B8",
      "to": "WALL::36",
      "relationship": "SUPPORTED_BY",
      "confidence": 0.94,
      "end": "end",
      "legacy_from": "B8",
      "legacy_to": "WALL_36"
    },
    {
      "from": "BEAM::B8",
      "to": "WALL::36",
      "relationship": "CONNECTED_TO",
      "confidence": 0.94,
      "legacy_from": "B8",
      "legacy_to": "WALL_36"
    },
    {
      "from": "BEAM::B9",
      "to": "COLUMN::4",
      "relationship": "SUPPORTED_BY",
      "confidence": 0.97,
      "end": "start",
      "legacy_from": "B9",
      "legacy_to": "COLUMN_4"
    },
    {
      "from": "BEAM::B9",
      "to": "COLUMN::4",
      "relationship": "CONNECTED_TO",
      "confidence": 0.97,
      "legacy_from": "B9",
      "legacy_to": "COLUMN_4"
    },
    {
      "from": "BEAM::B10",
      "to": "BEAM::B11",
      "relationship": "SUPPORTED_BY",
      "confidence": 0.93,
      "end": "start",
      "legacy_from": "B10",
      "legacy_to": "B11"
    },
    {
      "from": "BEAM::B10",
      "to": "BEAM::B11",
      "relationship": "CONNECTED_TO",
      "confidence": 0.93,
      "legacy_from": "B10",
      "legacy_to": "B11"
    },
    {
      "from": "BEAM::B11",
      "to": "BEAM::B10",
      "relationship": "SUPPORTED_BY",
      "confidence": 0.93,
      "end": "start",
      "legacy_from": "B11",
      "legacy_to": "B10"
    },
    {
      "from": "BEAM::B11",
      "to": "BEAM::B10",
      "relationship": "CONNECTED_TO",
      "confidence": 0.93,
      "legacy_from": "B11",
      "legacy_to": "B10"
    },
    {
      "from": "BEAM::B11",
      "to": "WALL::45",
      "relationship": "SUPPORTED_BY",
      "confidence": 0.94,
      "end": "end",
      "legacy_from": "B11",
      "legacy_to": "WALL_45"
    },
    {
      "from": "BEAM::B11",
      "to": "WALL::45",
      "relationship": "CONNECTED_TO",
      "confidence": 0.94,
      "legacy_from": "B11",
      "legacy_to": "WALL_45"
    },
    {
      "from": "BEAM::B12",
      "to": "BEAM::B4",
      "relationship": "SUPPORTED_BY",
      "confidence": 0.93,
      "end": "start",
      "legacy_from": "B12",
      "legacy_to": "B4"
    },
    {
      "from": "BEAM::B12",
      "to": "BEAM::B4",
      "relationship": "CONNECTED_TO",
      "confidence": 0.93,
      "legacy_from": "B12",
      "legacy_to": "B4"
    },
    {
      "from": "BEAM::B12",
      "to": "BEAM::B5",
      "relationship": "SUPPORTED_BY",
      "confidence": 0.93,
      "end": "end",
      "legacy_from": "B12",
      "legacy_to": "B5"
    },
    {
      "from": "BEAM::B12",
      "to": "BEAM::B5",
      "relationship": "CONNECTED_TO",
      "confidence": 0.93,
      "legacy_from": "B12",
      "legacy_to": "B5"
    },
    {
      "from": "BEAM::B13",
      "to": "BEAM::B4",
      "relationship": "SUPPORTED_BY",
      "confidence": 0.93,
      "end": "start",
      "legacy_from": "B13",
      "legacy_to": "B4"
    },
    {
      "from": "BEAM::B13",
      "to": "BEAM::B4",
      "relationship": "CONNECTED_TO",
      "confidence": 0.93,
      "legacy_from": "B13",
      "legacy_to": "B4"
    },
    {
      "from": "BEAM::B13",
      "to": "BEAM::B5",
      "relationship": "SUPPORTED_BY",
      "confidence": 0.93,
      "end": "end",
      "legacy_from": "B13",
      "legacy_to": "B5"
    },
    {
      "from": "BEAM::B13",
      "to": "BEAM::B5",
      "relationship": "CONNECTED_TO",
      "confidence": 0.93,
      "legacy_from": "B13",
      "legacy_to": "B5"
    },
    {
      "from": "BEAM::B14",
      "to": "WALL::43",
      "relationship": "SUPPORTED_BY",
      "confidence": 0.94,
      "end": "start",
      "legacy_from": "B14",
      "legacy_to": "WALL_43"
    },
    {
      "from": "BEAM::B14",
      "to": "WALL::43",
      "relationship": "CONNECTED_TO",
      "confidence": 0.94,
      "legacy_from": "B14",
      "legacy_to": "WALL_43"
    },
    {
      "from": "BEAM::B14",
      "to": "WALL::34",
      "relationship": "SUPPORTED_BY",
      "confidence": 0.94,
      "end": "end",
      "legacy_from": "B14",
      "legacy_to": "WALL_34"
    },
    {
      "from": "BEAM::B14",
      "to": "WALL::34",
      "relationship": "CONNECTED_TO",
      "confidence": 0.94,
      "legacy_from": "B14",
      "legacy_to": "WALL_34"
    },
    {
      "from": "BEAM::B15",
      "to": "WALL::74",
      "relationship": "SUPPORTED_BY",
      "confidence": 0.94,
      "end": "start",
      "legacy_from": "B15",
      "legacy_to": "WALL_74"
    },
    {
      "from": "BEAM::B15",
      "to": "WALL::74",
      "relationship": "CONNECTED_TO",
      "confidence": 0.94,
      "legacy_from": "B15",
      "legacy_to": "WALL_74"
    },
    {
      "from": "BEAM::B15",
      "to": "WALL::77",
      "relationship": "SUPPORTED_BY",
      "confidence": 0.94,
      "end": "end",
      "legacy_from": "B15",
      "legacy_to": "WALL_77"
    },
    {
      "from": "BEAM::B15",
      "to": "WALL::77",
      "relationship": "CONNECTED_TO",
      "confidence": 0.94,
      "legacy_from": "B15",
      "legacy_to": "WALL_77"
    },
    {
      "from": "BEAM::B16",
      "to": "WALL::58",
      "relationship": "SUPPORTED_BY",
      "confidence": 0.94,
      "end": "start",
      "legacy_from": "B16",
      "legacy_to": "WALL_58"
    },
    {
      "from": "BEAM::B16",
      "to": "WALL::58",
      "relationship": "CONNECTED_TO",
      "confidence": 0.94,
      "legacy_from": "B16",
      "legacy_to": "WALL_58"
    },
    {
      "from": "BEAM::B16",
      "to": "WALL::50",
      "relationship": "SUPPORTED_BY",
      "confidence": 0.94,
      "end": "end",
      "legacy_from": "B16",
      "legacy_to": "WALL_50"
    },
    {
      "from": "BEAM::B16",
      "to": "WALL::50",
      "relationship": "CONNECTED_TO",
      "confidence": 0.94,
      "legacy_from": "B16",
      "legacy_to": "WALL_50"
    },
    {
      "from": "BEAM::B17",
      "to": "WALL::79",
      "relationship": "SUPPORTED_BY",
      "confidence": 0.94,
      "end": "start",
      "legacy_from": "B17",
      "legacy_to": "WALL_79"
    },
    {
      "from": "BEAM::B17",
      "to": "WALL::79",
      "relationship": "CONNECTED_TO",
      "confidence": 0.94,
      "legacy_from": "B17",
      "legacy_to": "WALL_79"
    },
    {
      "from": "BEAM::B17",
      "to": "WALL::47",
      "relationship": "SUPPORTED_BY",
      "confidence": 0.94,
      "end": "end",
      "legacy_from": "B17",
      "legacy_to": "WALL_47"
    },
    {
      "from": "BEAM::B17",
      "to": "WALL::47",
      "relationship": "CONNECTED_TO",
      "confidence": 0.94,
      "legacy_from": "B17",
      "legacy_to": "WALL_47"
    },
    {
      "from": "BEAM::B18",
      "to": "WALL::79",
      "relationship": "SUPPORTED_BY",
      "confidence": 0.94,
      "end": "start",
      "legacy_from": "B18",
      "legacy_to": "WALL_79"
    },
    {
      "from": "BEAM::B18",
      "to": "WALL::79",
      "relationship": "CONNECTED_TO",
      "confidence": 0.94,
      "legacy_from": "B18",
      "legacy_to": "WALL_79"
    },
    {
      "from": "BEAM::B18",
      "to": "WALL::77",
      "relationship": "SUPPORTED_BY",
      "confidence": 0.94,
      "end": "end",
      "legacy_from": "B18",
      "legacy_to": "WALL_77"
    },
    {
      "from": "BEAM::B18",
      "to": "WALL::77",
      "relationship": "CONNECTED_TO",
      "confidence": 0.94,
      "legacy_from": "B18",
      "legacy_to": "WALL_77"
    },
    {
      "from": "BEAM::B4",
      "to": "BEAM::B5",
      "relationship": "CONTINUOUS_WITH",
      "confidence": 0.88,
      "via_support": "B12",
      "legacy_from": "B4",
      "legacy_to": "B5"
    },
    {
      "from": "BEAM::B12",
      "to": "BEAM::B13",
      "relationship": "CONTINUOUS_WITH",
      "confidence": 0.88,
      "via_support": "B4",
      "legacy_from": "B12",
      "legacy_to": "B13"
    },
    {
      "from": "BEAM::B2",
      "to": "BEAM::B15",
      "relationship": "CONTINUOUS_WITH",
      "confidence": 0.88,
      "via_support": "WALL_74",
      "legacy_from": "B2",
      "legacy_to": "B15"
    },
    {
      "from": "BEAM::B6",
      "to": "BEAM::B7",
      "relationship": "CONTINUOUS_WITH",
      "confidence": 0.88,
      "via_support": "WALL_77",
      "legacy_from": "B6",
      "legacy_to": "B7"
    },
    {
      "from": "BEAM::B6",
      "to": "BEAM::B15",
      "relationship": "CONTINUOUS_WITH",
      "confidence": 0.88,
      "via_support": "WALL_77",
      "legacy_from": "B6",
      "legacy_to": "B15"
    },
    {
      "from": "BEAM::B6",
      "to": "BEAM::B18",
      "relationship": "CONTINUOUS_WITH",
      "confidence": 0.88,
      "via_support": "WALL_77",
      "legacy_from": "B6",
      "legacy_to": "B18"
    },
    {
      "from": "BEAM::B7",
      "to": "BEAM::B15",
      "relationship": "CONTINUOUS_WITH",
      "confidence": 0.88,
      "via_support": "WALL_77",
      "legacy_from": "B7",
      "legacy_to": "B15"
    },
    {
      "from": "BEAM::B7",
      "to": "BEAM::B18",
      "relationship": "CONTINUOUS_WITH",
      "confidence": 0.88,
      "via_support": "WALL_77",
      "legacy_from": "B7",
      "legacy_to": "B18"
    },
    {
      "from": "BEAM::B15",
      "to": "BEAM::B18",
      "relationship": "CONTINUOUS_WITH",
      "confidence": 0.88,
      "via_support": "WALL_77",
      "legacy_from": "B15",
      "legacy_to": "B18"
    },
    {
      "from": "BEAM::B3",
      "to": "BEAM::B17",
      "relationship": "CONTINUOUS_WITH",
      "confidence": 0.88,
      "via_support": "WALL_79",
      "legacy_from": "B3",
      "legacy_to": "B17"
    },
    {
      "from": "BEAM::B3",
      "to": "BEAM::B18",
      "relationship": "CONTINUOUS_WITH",
      "confidence": 0.88,
      "via_support": "WALL_79",
      "legacy_from": "B3",
      "legacy_to": "B18"
    },
    {
      "from": "BEAM::B17",
      "to": "BEAM::B18",
      "relationship": "CONTINUOUS_WITH",
      "confidence": 0.88,
      "via_support": "WALL_79",
      "legacy_from": "B17",
      "legacy_to": "B18"
    },
    {
      "from": "BEAM::B2",
      "to": "BEAM::B15",
      "relationship": "INTERSECTS",
      "confidence": 0.9991,
      "distance_mm": 0.218,
      "legacy_from": "B2",
      "legacy_to": "B15"
    },
    {
      "from": "BEAM::B3",
      "to": "BEAM::B17",
      "relationship": "INTERSECTS",
      "confidence": 1.0,
      "distance_mm": 0.0,
      "legacy_from": "B3",
      "legacy_to": "B17"
    },
    {
      "from": "BEAM::B3",
      "to": "BEAM::B18",
      "relationship": "INTERSECTS",
      "confidence": 1.0,
      "distance_mm": 0.0,
      "legacy_from": "B3",
      "legacy_to": "B18"
    },
    {
      "from": "BEAM::B4",
      "to": "BEAM::B13",
      "relationship": "INTERSECTS",
      "confidence": 0.7,
      "distance_mm": 200.0,
      "legacy_from": "B4",
      "legacy_to": "B13"
    },
    {
      "from": "BEAM::B5",
      "to": "BEAM::B13",
      "relationship": "INTERSECTS",
      "confidence": 1.0,
      "distance_mm": 0.0,
      "legacy_from": "B5",
      "legacy_to": "B13"
    },
    {
      "from": "BEAM::B5",
      "to": "BEAM::B12",
      "relationship": "INTERSECTS",
      "confidence": 0.7,
      "distance_mm": 200.0,
      "legacy_from": "B5",
      "legacy_to": "B12"
    },
    {
      "from": "BEAM::B6",
      "to": "BEAM::B7",
      "relationship": "INTERSECTS",
      "confidence": 0.7,
      "distance_mm": 200.0,
      "legacy_from": "B6",
      "legacy_to": "B7"
    },
    {
      "from": "BEAM::B6",
      "to": "BEAM::B15",
      "relationship": "INTERSECTS",
      "confidence": 0.9797,
      "distance_mm": 5.073,
      "legacy_from": "B6",
      "legacy_to": "B15"
    },
    {
      "from": "BEAM::B7",
      "to": "BEAM::B15",
      "relationship": "INTERSECTS",
      "confidence": 0.7,
      "distance_mm": 200.062,
      "legacy_from": "B7",
      "legacy_to": "B15"
    },
    {
      "from": "BEAM::B7",
      "to": "BEAM::B18",
      "relationship": "INTERSECTS",
      "confidence": 1.0,
      "distance_mm": 0.0,
      "legacy_from": "B7",
      "legacy_to": "B18"
    },
    {
      "from": "BEAM::B10",
      "to": "BEAM::B11",
      "relationship": "INTERSECTS",
      "confidence": 0.7,
      "distance_mm": 200.031,
      "legacy_from": "B10",
      "legacy_to": "B11"
    },
    {
      "from": "BEAM::B4",
      "to": "BEAM::B13",
      "relationship": "CONTINUOUS_WITH",
      "confidence": 0.93,
      "joint_end": "left",
      "legacy_from": "B4",
      "legacy_to": "B13"
    },
    {
      "from": "BEAM::B4",
      "to": "BEAM::B12",
      "relationship": "CONTINUOUS_WITH",
      "confidence": 0.93,
      "joint_end": "right",
      "legacy_from": "B4",
      "legacy_to": "B12"
    },
    {
      "from": "BEAM::B5",
      "to": "BEAM::B13",
      "relationship": "CONTINUOUS_WITH",
      "confidence": 0.93,
      "joint_end": "left",
      "legacy_from": "B5",
      "legacy_to": "B13"
    },
    {
      "from": "BEAM::B5",
      "to": "BEAM::B12",
      "relationship": "CONTINUOUS_WITH",
      "confidence": 0.93,
      "joint_end": "right",
      "legacy_from": "B5",
      "legacy_to": "B12"
    }
  ]
}