{
  "phase": "Phase G.2",
  "text_objects": [
    {
      "geometry_id": "TXT::001",
      "engineering_object_id": null,
      "engineering_status": "GEOMETRY_ONLY",
      "status": "READY",
      "text": "B1(200X600)",
      "bbox": {
        "min_x": 6431.966,
        "min_y": 19518.021,
        "max_x": 7666.892,
        "max_y": 19709.896
      },
      "layer": "SEC TEXT",
      "rotation": 359.989,
      "height": 150.0,
      "entity_type": "TEXT",
      "ownership": {
        "owner_type": "ENGINEERING_REINFORCEMENT_CONTEXT",
        "owner_id": "ERC::B1",
        "ownership_source": "BEAM_MATCH",
        "ownership_confidence": 1.0
      }
    },
    {
      "geometry_id": "TXT::002",
      "engineering_object_id": null,
      "engineering_status": "GEOMETRY_ONLY",
      "status": "READY",
      "text": "2-Y16",
      "bbox": {
        "min_x": 7758.83,
        "min_y": 22393.046,
        "max_x": 8224.809,
        "max_y": 22552.749
      },
      "layer": "-STR-TEXT",
      "rotation": 0.0,
      "height": 125.0,
      "entity_type": "MTEXT",
      "ownership": {
        "owner_type": "ENGINEERING_REINFORCEMENT_CONTEXT",
        "owner_id": "ERC::B8",
        "ownership_source": "BEAM_MATCH",
        "ownership_confidence": 1.0
      }
    },
    {
      "geometry_id": "TXT::003",
      "engineering_object_id": null,
      "engineering_status": "GEOMETRY_ONLY",
      "status": "READY",
      "text": "2-Y16",
      "bbox": {
        "min_x": 5011.763,
        "min_y": 22238.598,
        "max_x": 5477.742,
        "max_y": 22398.301
      },
      "layer": "-STR-TEXT",
      "rotation": 0.0,
      "height": 125.0,
      "entity_type": "MTEXT",
      "ownership": {
        "owner_type": "ENGINEERING_REINFORCEMENT_CONTEXT",
        "owner_id": "ERC::B8",
        "ownership_source": "BEAM_MATCH",
        "ownership_confidence": 1.0
      }
    },
    {
      "geometry_id": "TXT::004",
      "engineering_object_id": null,
      "engineering_status": "GEOMETRY_ONLY",
      "status": "READY",
      "text": "2-Y20",
      "bbox": {
        "min_x": 8689.362,
        "min_y": 20479.415,
        "max_x": 9155.341,
        "max_y": 20639.118
      },
      "layer": "-STR-TEXT",
      "rotation": 0.0,
      "height": 125.0,
      "entity_type": "MTEXT",
      "ownership": {
        "owner_type": "ENGINEERING_REINFORCEMENT_CONTEXT",
        "owner_id": "ERC::B1",
        "ownership_source": "BEAM_MATCH",
        "ownership_confidence": 1.0
      }
    },
    {
      "geometry_id": "TXT::005",
      "engineering_object_id": null,
      "engineering_status": "GEOMETRY_ONLY",
      "status": "READY",
      "text": "2-Y16",
      "bbox": {
        "min_x": 6482.974,
        "min_y": 21872.658,
        "max_x": 6948.953,
        "max_y": 22032.361
      },
      "layer": "-STR-TEXT",
      "rotation": 0.0,
      "height": 125.0,
      "entity_type": "MTEXT",
      "ownership": {
        "owner_type": "ENGINEERING_REINFORCEMENT_CONTEXT",
        "owner_id": "ERC::B8",
        "ownership_source": "BEAM_MATCH",
        "ownership_confidence": 1.0
      }
    },
    {
      "geometry_id": "TXT::006",
      "engineering_object_id": null,
      "engineering_status": "GEOMETRY_ONLY",
      "status": "READY",
      "text": "2-Y20",
      "bbox": {
        "min_x": 7588.574,
        "min_y": 20493.059,
        "max_x": 7869.96,
        "max_y": 20652.763
      },
      "layer": "-STR-TEXT",
      "rotation": 0.0,
      "height": 125.0,
      "entity_type": "MTEXT",
      "ownership": {
        "owner_type": "ENGINEERING_REINFORCEMENT_CONTEXT",
        "owner_id": "ERC::B1",
        "ownership_source": "BEAM_MATCH",
        "ownership_confidence": 1.0
      }
    },
    {
      "geometry_id": "TXT::007",
      "engineering_object_id": null,
      "engineering_status": "GEOMETRY_ONLY",
      "status": "READY",
      "text": "B3(200X600)",
      "bbox": {
        "min_x": 21373.106,
        "min_y": 19556.437,
        "max_x": 22666.252,
        "max_y": 19748.323
      },
      "layer": "SEC TEXT",
      "rotation": 359.989,
      "height": 150.0,
      "entity_type": "TEXT",
      "ownership": {
        "owner_type": "ENGINEERING_REINFORCEMENT_CONTEXT",
        "owner_id": "ERC::B3",
        "ownership_source": "BEAM_MATCH",
        "ownership_confidence": 1.0
      }
    },
    {
      "geometry_id": "TXT::008",
      "engineering_object_id": null,
      "engineering_status": "GEOMETRY_ONLY",
      "status": "READY",
      "text": "2-Y20",
      "bbox": {
        "min_x": 23361.426,
        "min_y": 20668.639,
        "max_x": 23642.812,
        "max_y": 20828.342
      },
      "layer": "-STR-TEXT",
      "rotation": 0.0,
      "height": 125.0,
      "entity_type": "MTEXT",
      "ownership": {
        "owner_type": "ENGINEERING_REINFORCEMENT_CONTEXT",
        "owner_id": "ERC::B3",
        "ownership_source": "BEAM_MATCH",
        "ownership_confidence": 1.0
      }
    },
    {
      "geometry_id": "TXT::009",
      "engineering_object_id": null,
      "engineering_status": "GEOMETRY_ONLY",
      "status": "READY",
      "text": "2-Y20",
      "bbox": {
        "min_x": 23099.603,
        "min_y": 21905.758,
        "max_x": 23565.582,
        "max_y": 22065.461
      },
      "layer": "-STR-TEXT",
      "rotation": 0.0,
      "height": 125.0,
      "entity_type": "MTEXT",
      "ownership": {
        "owner_type": "ENGINEERING_REINFORCEMENT_CONTEXT",
        "owner_id": "ERC::B8",
        "ownership_source": "BEAM_MATCH",
        "ownership_confidence": 1.0
      }
    },
    {
      "geometry_id": "TXT::010",
      "engineering_object_id": null,
      "engineering_status": "GEOMETRY_ONLY",
      "status": "READY",
      "text": "B3(200X600)",
      "bbox": {
        "min_x": 22991.799,
        "min_y": 19577.231,
        "max_x": 24284.946,
        "max_y": 19769.117
      },
      "layer": "SEC TEXT",
      "rotation": 359.989,
      "height": 150.0,
      "entity_type": "TEXT",
      "ownership": {
        "owner_type": "ENGINEERING_REINFORCEMENT_CONTEXT",
        "owner_id": "ERC::B3",
        "ownership_source": "BEAM_MATCH",
        "ownership_confidence": 1.0
      }
    },
    {
      "geometry_id": "TXT::011",
      "engineering_object_id": null,
      "engineering_status": "GEOMETRY_ONLY",
      "status": "READY",
      "text": "B2(200X600)",
      "bbox": {
        "min_x": 16292.823,
        "min_y": 19759.991,
        "max_x": 17585.969,
        "max_y": 19951.877
      },
      "layer": "SEC TEXT",
      "rotation": 359.989,
      "height": 150.0,
      "entity_type": "TEXT",
      "ownership": {
        "owner_type": "ENGINEERING_REINFORCEMENT_CONTEXT",
        "owner_id": "ERC::B2",
        "ownership_source": "BEAM_MATCH",
        "ownership_confidence": 1.0
      }
    },
    {
      "geometry_id": "TXT::012",
      "engineering_object_id": null,
      "engineering_status": "GEOMETRY_ONLY",
      "status": "READY",
      "text": "2-Y20",
      "bbox": {
        "min_x": 13940.408,
        "min_y": 20697.356,
        "max_x": 14221.794,
        "max_y": 20857.06
      },
      "layer": "-STR-TEXT",
      "rotation": 0.0,
      "height": 125.0,
      "entity_type": "MTEXT",
      "ownership": {
        "owner_type": "ENGINEERING_REINFORCEMENT_CONTEXT",
        "owner_id": "ERC::B2",
        "ownership_source": "BEAM_MATCH",
        "ownership_confidence": 1.0
      }
    },
    {
      "geometry_id": "TXT::013",
      "engineering_object_id": null,
      "engineering_status": "GEOMETRY_ONLY",
      "status": "READY",
      "text": "2-Y16",
      "bbox": {
        "min_x": 14797.618,
        "min_y": 21925.426,
        "max_x": 15263.597,
        "max_y": 22085.13
      },
      "layer": "-STR-TEXT",
      "rotation": 0.0,
      "height": 125.0,
      "entity_type": "MTEXT",
      "ownership": {
        "owner_type": "ENGINEERING_REINFORCEMENT_CONTEXT",
        "owner_id": "ERC::B8",
        "ownership_source": "BEAM_MATCH",
        "ownership_confidence": 1.0
      }
    },
    {
      "geometry_id": "TXT::014",
      "engineering_object_id": null,
      "engineering_status": "GEOMETRY_ONLY",
      "status": "READY",
      "text": "2-Y12",
      "bbox": {
        "min_x": 16868.391,
        "min_y": 20549.71,
        "max_x": 17149.777,
        "max_y": 20709.413
      },
      "layer": "-STR-TEXT",
      "rotation": 0.0,
      "height": 125.0,
      "entity_type": "MTEXT",
      "ownership": {
        "owner_type": "ENGINEERING_REINFORCEMENT_CONTEXT",
        "owner_id": "ERC::B2",
        "ownership_source": "BEAM_MATCH",
        "ownership_confidence": 1.0
      }
    },
    {
      "geometry_id": "TXT::015",
      "engineering_object_id": null,
      "engineering_status": "GEOMETRY_ONLY",
      "status": "READY",
      "text": "B4(200X600)",
      "bbox": {
        "min_x": 28737.809,
        "min_y": 19595.425,
        "max_x": 30030.956,
        "max_y": 19787.311
      },
      "layer": "SEC TEXT",
      "rotation": 359.989,
      "height": 150.0,
      "entity_type": "TEXT",
      "ownership": {
        "owner_type": "ENGINEERING_REINFORCEMENT_CONTEXT",
        "owner_id": "ERC::B4",
        "ownership_source": "BEAM_MATCH",
        "ownership_confidence": 1.0
      }
    },
    {
      "geometry_id": "TXT::016",
      "engineering_object_id": null,
      "engineering_status": "GEOMETRY_ONLY",
      "status": "READY",
      "text": "2-Y20",
      "bbox": {
        "min_x": 26385.395,
        "min_y": 20532.79,
        "max_x": 26666.781,
        "max_y": 20692.494
      },
      "layer": "-STR-TEXT",
      "rotation": 0.0,
      "height": 125.0,
      "entity_type": "MTEXT",
      "ownership": {
        "owner_type": "ENGINEERING_REINFORCEMENT_CONTEXT",
        "owner_id": "ERC::B4",
        "ownership_source": "BEAM_MATCH",
        "ownership_confidence": 1.0
      }
    },
    {
      "geometry_id": "TXT::017",
      "engineering_object_id": null,
      "engineering_status": "GEOMETRY_ONLY",
      "status": "READY",
      "text": "2-Y16",
      "bbox": {
        "min_x": 27242.605,
        "min_y": 21760.86,
        "max_x": 27708.583,
        "max_y": 21920.564
      },
      "layer": "-STR-TEXT",
      "rotation": 0.0,
      "height": 125.0,
      "entity_type": "MTEXT",
      "ownership": {
        "owner_type": "ENGINEERING_REINFORCEMENT_CONTEXT",
        "owner_id": "ERC::B8",
        "ownership_source": "BEAM_MATCH",
        "ownership_confidence": 1.0
      }
    },
    {
      "geometry_id": "TXT::018",
      "engineering_object_id": null,
      "engineering_status": "GEOMETRY_ONLY",
      "status": "READY",
      "text": "2-Y16",
      "bbox": {
        "min_x": 29313.378,
        "min_y": 20385.144,
        "max_x": 29594.763,
        "max_y": 20544.847
      },
      "layer": "-STR-TEXT",
      "rotation": 0.0,
      "height": 125.0,
      "entity_type": "MTEXT",
      "ownership": {
        "owner_type": "ENGINEERING_REINFORCEMENT_CONTEXT",
        "owner_id": "ERC::B4",
        "ownership_source": "BEAM_MATCH",
        "ownership_confidence": 1.0
      }
    },
    {
      "geometry_id": "TXT::019",
      "engineering_object_id": null,
      "engineering_status": "GEOMETRY_ONLY",
      "status": "READY",
      "text": "2-Y12",
      "bbox": {
        "min_x": 30580.045,
        "min_y": 22141.406,
        "max_x": 31046.024,
        "max_y": 22301.109
      },
      "layer": "-STR-TEXT",
      "rotation": 0.0,
      "height": 125.0,
      "entity_type": "MTEXT",
      "ownership": {
        "owner_type": "ENGINEERING_REINFORCEMENT_CONTEXT",
        "owner_id": "ERC::B8",
        "ownership_source": "BEAM_MATCH",
        "ownership_confidence": 1.0
      }
    },
    {
      "geometry_id": "TXT::020",
      "engineering_object_id": null,
      "engineering_status": "GEOMETRY_ONLY",
      "status": "READY",
      "text": "2-Y20",
      "bbox": {
        "min_x": 10759.307,
        "min_y": 17379.366,
        "max_x": 11455.692,
        "max_y": 17539.069
      },
      "layer": "-STR-TEXT",
      "rotation": 0.0,
      "height": 125.0,
      "entity_type": "MTEXT",
      "ownership": {
        "owner_type": "ENGINEERING_REINFORCEMENT_CONTEXT",
        "owner_id": "ERC::B1",
        "ownership_source": "BEAM_MATCH",
        "ownership_confidence": 1.0
      }
    },
    {
      "geometry_id": "TXT::021",
      "engineering_object_id": null,
      "engineering_status": "GEOMETRY_ONLY",
      "status": "READY",
      "text": "2-Y20",
      "bbox": {
        "min_x": 11130.4,
        "min_y": 18504.924,
        "max_x": 11596.379,
        "max_y": 18664.627
      },
      "layer": "-STR-TEXT",
      "rotation": 0.0,
      "height": 125.0,
      "entity_type": "MTEXT",
      "ownership": {
        "owner_type": "ENGINEERING_REINFORCEMENT_CONTEXT",
        "owner_id": "ERC::B1",
        "ownership_source": "BEAM_MATCH",
        "ownership_confidence": 1.0
      }
    },
    {
      "geometry_id": "TXT::022",
      "engineering_object_id": null,
      "engineering_status": "GEOMETRY_ONLY",
      "status": "READY",
      "text": "B6(200X600)",
      "bbox": {
        "min_x": 10832.476,
        "min_y": 16133.92,
        "max_x": 12067.403,
        "max_y": 16325.795
      },
      "layer": "SEC TEXT",
      "rotation": 0.011,
      "height": 150.0,
      "entity_type": "TEXT",
      "ownership": {
        "owner_type": "ENGINEERING_REINFORCEMENT_CONTEXT",
        "owner_id": "ERC::B1",
        "ownership_source": "BEAM_MATCH",
        "ownership_confidence": 1.0
      }
    },
    {
      "geometry_id": "TXT::023",
      "engineering_object_id": null,
      "engineering_status": "GEOMETRY_ONLY",
      "status": "READY",
      "text": "2-Y20",
      "bbox": {
        "min_x": 15850.347,
        "min_y": 17375.493,
        "max_x": 16546.732,
        "max_y": 17535.196
      },
      "layer": "-STR-TEXT",
      "rotation": 0.0,
      "height": 125.0,
      "entity_type": "MTEXT",
      "ownership": {
        "owner_type": "ENGINEERING_REINFORCEMENT_CONTEXT",
        "owner_id": "ERC::B2",
        "ownership_source": "BEAM_MATCH",
        "ownership_confidence": 1.0
      }
    },
    {
      "geometry_id": "TXT::024",
      "engineering_object_id": null,
      "engineering_status": "GEOMETRY_ONLY",
      "status": "READY",
      "text": "2-Y20",
      "bbox": {
        "min_x": 15150.544,
        "min_y": 18453.563,
        "max_x": 15616.523,
        "max_y": 18613.266
      },
      "layer": "-STR-TEXT",
      "rotation": 0.0,
      "height": 125.0,
      "entity_type": "MTEXT",
      "ownership": {
        "owner_type": "ENGINEERING_REINFORCEMENT_CONTEXT",
        "owner_id": "ERC::B2",
        "ownership_source": "BEAM_MATCH",
        "ownership_confidence": 1.0
      }
    },
    {
      "geometry_id": "TXT::025",
      "engineering_object_id": null,
      "engineering_status": "GEOMETRY_ONLY",
      "status": "READY",
      "text": "2-Y16",
      "bbox": {
        "min_x": 16381.861,
        "min_y": 18810.179,
        "max_x": 16847.84,
        "max_y": 18969.882
      },
      "layer": "-STR-TEXT",
      "rotation": 0.0,
      "height": 125.0,
      "entity_type": "MTEXT",
      "ownership": {
        "owner_type": "ENGINEERING_REINFORCEMENT_CONTEXT",
        "owner_id": "ERC::B2",
        "ownership_source": "BEAM_MATCH",
        "ownership_confidence": 1.0
      }
    },
    {
      "geometry_id": "TXT::026",
      "engineering_object_id": null,
      "engineering_status": "GEOMETRY_ONLY",
      "status": "READY",
      "text": "B7(200X600)",
      "bbox": {
        "min_x": 15927.064,
        "min_y": 15998.768,
        "max_x": 17161.991,
        "max_y": 16190.643
      },
      "layer": "SEC TEXT",
      "rotation": 0.011,
      "height": 150.0,
      "entity_type": "TEXT",
      "ownership": {
        "owner_type": "ENGINEERING_REINFORCEMENT_CONTEXT",
        "owner_id": "ERC::B2",
        "ownership_source": "BEAM_MATCH",
        "ownership_confidence": 1.0
      }
    },
    {
      "geometry_id": "TXT::027",
      "engineering_object_id": null,
      "engineering_status": "GEOMETRY_ONLY",
      "status": "READY",
      "text": "2-Y16",
      "bbox": {
        "min_x": 20636.29,
        "min_y": 18507.169,
        "max_x": 21102.269,
        "max_y": 18666.872
      },
      "layer": "-STR-TEXT",
      "rotation": 0.0,
      "height": 125.0,
      "entity_type": "MTEXT",
      "ownership": {
        "owner_type": "ENGINEERING_REINFORCEMENT_CONTEXT",
        "owner_id": "ERC::B3",
        "ownership_source": "BEAM_MATCH",
        "ownership_confidence": 1.0
      }
    },
    {
      "geometry_id": "TXT::028",
      "engineering_object_id": null,
      "engineering_status": "GEOMETRY_ONLY",
      "status": "READY",
      "text": "2-Y16",
      "bbox": {
        "min_x": 20636.29,
        "min_y": 17049.094,
        "max_x": 21102.269,
        "max_y": 17208.797
      },
      "layer": "-STR-TEXT",
      "rotation": 0.0,
      "height": 125.0,
      "entity_type": "MTEXT",
      "ownership": {
        "owner_type": "ENGINEERING_REINFORCEMENT_CONTEXT",
        "owner_id": "ERC::B3",
        "ownership_source": "BEAM_MATCH",
        "ownership_confidence": 1.0
      }
    },
    {
      "geometry_id": "TXT::029",
      "engineering_object_id": null,
      "engineering_status": "GEOMETRY_ONLY",
      "status": "READY",
      "text": "2-Y16",
      "bbox": {
        "min_x": 24105.136,
        "min_y": 18507.169,
        "max_x": 24571.115,
        "max_y": 18666.872
      },
      "layer": "-STR-TEXT",
      "rotation": 0.0,
      "height": 125.0,
      "entity_type": "MTEXT",
      "ownership": {
        "owner_type": "ENGINEERING_REINFORCEMENT_CONTEXT",
        "owner_id": "ERC::B3",
        "ownership_source": "BEAM_MATCH",
        "ownership_confidence": 1.0
      }
    },
    {
      "geometry_id": "TXT::030",
      "engineering_object_id": null,
      "engineering_status": "GEOMETRY_ONLY",
      "status": "READY",
      "text": "2-Y16",
      "bbox": {
        "min_x": 24105.136,
        "min_y": 17049.094,
        "max_x": 24571.115,
        "max_y": 17208.797
      },
      "layer": "-STR-TEXT",
      "rotation": 0.0,
      "height": 125.0,
      "entity_type": "MTEXT",
      "ownership": {
        "owner_type": "ENGINEERING_REINFORCEMENT_CONTEXT",
        "owner_id": "ERC::B3",
        "ownership_source": "BEAM_MATCH",
        "ownership_confidence": 1.0
      }
    },
    {
      "geometry_id": "TXT::031",
      "engineering_object_id": null,
      "engineering_status": "GEOMETRY_ONLY",
      "status": "READY",
      "text": "2-Y16",
      "bbox": {
        "min_x": 27681.813,
        "min_y": 18507.169,
        "max_x": 28147.791,
        "max_y": 18666.872
      },
      "layer": "-STR-TEXT",
      "rotation": 0.0,
      "height": 125.0,
      "entity_type": "MTEXT",
      "ownership": {
        "owner_type": "ENGINEERING_REINFORCEMENT_CONTEXT",
        "owner_id": "ERC::B4",
        "ownership_source": "BEAM_MATCH",
        "ownership_confidence": 1.0
      }
    },
    {
      "geometry_id": "TXT::032",
      "engineering_object_id": null,
      "engineering_status": "GEOMETRY_ONLY",
      "status": "READY",
      "text": "2-Y16",
      "bbox": {
        "min_x": 27681.813,
        "min_y": 17049.094,
        "max_x": 28147.791,
        "max_y": 17208.797
      },
      "layer": "-STR-TEXT",
      "rotation": 0.0,
      "height": 125.0,
      "entity_type": "MTEXT",
      "ownership": {
        "owner_type": "ENGINEERING_REINFORCEMENT_CONTEXT",
        "owner_id": "ERC::B4",
        "ownership_source": "BEAM_MATCH",
        "ownership_confidence": 1.0
      }
    },
    {
      "geometry_id": "TXT::033",
      "engineering_object_id": null,
      "engineering_status": "GEOMETRY_ONLY",
      "status": "READY",
      "text": "B8(200X600)",
      "bbox": {
        "min_x": 20254.791,
        "min_y": 16039.605,
        "max_x": 21489.718,
        "max_y": 16231.48
      },
      "layer": "SEC TEXT",
      "rotation": 0.011,
      "height": 150.0,
      "entity_type": "TEXT",
      "ownership": {
        "owner_type": "ENGINEERING_REINFORCEMENT_CONTEXT",
        "owner_id": "ERC::B3",
        "ownership_source": "BEAM_MATCH",
        "ownership_confidence": 1.0
      }
    },
    {
      "geometry_id": "TXT::034",
      "engineering_object_id": null,
      "engineering_status": "GEOMETRY_ONLY",
      "status": "READY",
      "text": "B9(200X600)",
      "bbox": {
        "min_x": 23430.884,
        "min_y": 16039.605,
        "max_x": 24665.81,
        "max_y": 16231.48
      },
      "layer": "SEC TEXT",
      "rotation": 0.011,
      "height": 150.0,
      "entity_type": "TEXT",
      "ownership": {
        "owner_type": "ENGINEERING_REINFORCEMENT_CONTEXT",
        "owner_id": "ERC::B3",
        "ownership_source": "BEAM_MATCH",
        "ownership_confidence": 1.0
      }
    },
    {
      "geometry_id": "TXT::035",
      "engineering_object_id": null,
      "engineering_status": "GEOMETRY_ONLY",
      "status": "READY",
      "text": "B10(200X600)",
      "bbox": {
        "min_x": 27381.949,
        "min_y": 16042.923,
        "max_x": 28733.417,
        "max_y": 16234.82
      },
      "layer": "SEC TEXT",
      "rotation": 0.011,
      "height": 150.0,
      "entity_type": "TEXT",
      "ownership": {
        "owner_type": "ENGINEERING_REINFORCEMENT_CONTEXT",
        "owner_id": "ERC::B4",
        "ownership_source": "BEAM_MATCH",
        "ownership_confidence": 1.0
      }
    },
    {
      "geometry_id": "TXT::036",
      "engineering_object_id": null,
      "engineering_status": "GEOMETRY_ONLY",
      "status": "READY",
      "text": "B11(150X600)",
      "bbox": {
        "min_x": 33213.135,
        "min_y": 16091.073,
        "max_x": 34564.604,
        "max_y": 16282.97
      },
      "layer": "SEC TEXT",
      "rotation": 359.989,
      "height": 150.0,
      "entity_type": "TEXT",
      "ownership": {
        "owner_type": "ENGINEERING_REINFORCEMENT_CONTEXT",
        "owner_id": "ERC::B11",
        "ownership_source": "BEAM_MATCH",
        "ownership_confidence": 1.0
      }
    },
    {
      "geometry_id": "TXT::037",
      "engineering_object_id": null,
      "engineering_status": "GEOMETRY_ONLY",
      "status": "READY",
      "text": "2-Y16",
      "bbox": {
        "min_x": 33739.379,
        "min_y": 17059.712,
        "max_x": 34205.358,
        "max_y": 17219.416
      },
      "layer": "-STR-TEXT",
      "rotation": 0.0,
      "height": 125.0,
      "entity_type": "MTEXT",
      "ownership": {
        "owner_type": "ENGINEERING_REINFORCEMENT_CONTEXT",
        "owner_id": "ERC::B11",
        "ownership_source": "BEAM_MATCH",
        "ownership_confidence": 1.0
      }
    },
    {
      "geometry_id": "TXT::038",
      "engineering_object_id": null,
      "engineering_status": "GEOMETRY_ONLY",
      "status": "READY",
      "text": "2-Y16",
      "bbox": {
        "min_x": 33657.019,
        "min_y": 18452.955,
        "max_x": 34122.997,
        "max_y": 18612.659
      },
      "layer": "-STR-TEXT",
      "rotation": 0.0,
      "height": 125.0,
      "entity_type": "MTEXT",
      "ownership": {
        "owner_type": "ENGINEERING_REINFORCEMENT_CONTEXT",
        "owner_id": "ERC::B8",
        "ownership_source": "BEAM_MATCH",
        "ownership_confidence": 1.0
      }
    },
    {
      "geometry_id": "TXT::039",
      "engineering_object_id": null,
      "engineering_status": "GEOMETRY_ONLY",
      "status": "READY",
      "text": "B16(200X600)",
      "bbox": {
        "min_x": 4929.236,
        "min_y": 8977.601,
        "max_x": 6338.924,
        "max_y": 9169.509
      },
      "layer": "SEC TEXT",
      "rotation": 359.989,
      "height": 150.0,
      "entity_type": "TEXT",
      "ownership": {
        "owner_type": "ENGINEERING_REINFORCEMENT_CONTEXT",
        "owner_id": "ERC::B12",
        "ownership_source": "BEAM_MATCH",
        "ownership_confidence": 1.0
      }
    },
    {
      "geometry_id": "TXT::040",
      "engineering_object_id": null,
      "engineering_status": "GEOMETRY_ONLY",
      "status": "READY",
      "text": "2-Y16",
      "bbox": {
        "min_x": 5760.747,
        "min_y": 10095.655,
        "max_x": 6042.133,
        "max_y": 10255.359
      },
      "layer": "-STR-TEXT",
      "rotation": 0.0,
      "height": 125.0,
      "entity_type": "MTEXT",
      "ownership": {
        "owner_type": "ENGINEERING_REINFORCEMENT_CONTEXT",
        "owner_id": "ERC::B12",
        "ownership_source": "BEAM_MATCH",
        "ownership_confidence": 1.0
      }
    },
    {
      "geometry_id": "TXT::041",
      "engineering_object_id": null,
      "engineering_status": "GEOMETRY_ONLY",
      "status": "READY",
      "text": "2-Y16",
      "bbox": {
        "min_x": 5767.087,
        "min_y": 11337.168,
        "max_x": 6233.066,
        "max_y": 11496.871
      },
      "layer": "-STR-TEXT",
      "rotation": 0.0,
      "height": 125.0,
      "entity_type": "MTEXT",
      "ownership": {
        "owner_type": "ENGINEERING_REINFORCEMENT_CONTEXT",
        "owner_id": "ERC::B12",
        "ownership_source": "BEAM_MATCH",
        "ownership_confidence": 1.0
      }
    },
    {
      "geometry_id": "TXT::042",
      "engineering_object_id": null,
      "engineering_status": "GEOMETRY_ONLY",
      "status": "READY",
      "text": "B17(200X600)",
      "bbox": {
        "min_x": 9555.198,
        "min_y": 8944.249,
        "max_x": 10906.666,
        "max_y": 9136.146
      },
      "layer": "SEC TEXT",
      "rotation": 359.989,
      "height": 150.0,
      "entity_type": "TEXT",
      "ownership": {
        "owner_type": "ENGINEERING_REINFORCEMENT_CONTEXT",
        "owner_id": "ERC::B12",
        "ownership_source": "BEAM_MATCH",
        "ownership_confidence": 1.0
      }
    },
    {
      "geometry_id": "TXT::043",
      "engineering_object_id": null,
      "engineering_status": "GEOMETRY_ONLY",
      "status": "READY",
      "text": "2-Y20",
      "bbox": {
        "min_x": 9950.612,
        "min_y": 9940.456,
        "max_x": 10416.591,
        "max_y": 10100.159
      },
      "layer": "-STR-TEXT",
      "rotation": 0.0,
      "height": 125.0,
      "entity_type": "MTEXT",
      "ownership": {
        "owner_type": "ENGINEERING_REINFORCEMENT_CONTEXT",
        "owner_id": "ERC::B12",
        "ownership_source": "BEAM_MATCH",
        "ownership_confidence": 1.0
      }
    },
    {
      "geometry_id": "TXT::044",
      "engineering_object_id": null,
      "engineering_status": "GEOMETRY_ONLY",
      "status": "READY",
      "text": "2-Y20",
      "bbox": {
        "min_x": 9868.252,
        "min_y": 11333.699,
        "max_x": 10334.23,
        "max_y": 11493.402
      },
      "layer": "-STR-TEXT",
      "rotation": 0.0,
      "height": 125.0,
      "entity_type": "MTEXT",
      "ownership": {
        "owner_type": "ENGINEERING_REINFORCEMENT_CONTEXT",
        "owner_id": "ERC::B12",
        "ownership_source": "BEAM_MATCH",
        "ownership_confidence": 1.0
      }
    },
    {
      "geometry_id": "TXT::045",
      "engineering_object_id": null,
      "engineering_status": "GEOMETRY_ONLY",
      "status": "READY",
      "text": "2-Y20",
      "bbox": {
        "min_x": 12553.011,
        "min_y": 10074.881,
        "max_x": 13382.974,
        "max_y": 10234.584
      },
      "layer": "-STR-TEXT",
      "rotation": 0.0,
      "height": 125.0,
      "entity_type": "MTEXT",
      "ownership": {
        "owner_type": "ENGINEERING_REINFORCEMENT_CONTEXT",
        "owner_id": "ERC::B12",
        "ownership_source": "BEAM_MATCH",
        "ownership_confidence": 1.0
      }
    },
    {
      "geometry_id": "TXT::046",
      "engineering_object_id": null,
      "engineering_status": "GEOMETRY_ONLY",
      "status": "READY",
      "text": "2-Y20",
      "bbox": {
        "min_x": 12738.907,
        "min_y": 11311.999,
        "max_x": 13204.886,
        "max_y": 11471.702
      },
      "layer": "-STR-TEXT",
      "rotation": 0.0,
      "height": 125.0,
      "entity_type": "MTEXT",
      "ownership": {
        "owner_type": "ENGINEERING_REINFORCEMENT_CONTEXT",
        "owner_id": "ERC::B12",
        "ownership_source": "BEAM_MATCH",
        "ownership_confidence": 1.0
      }
    },
    {
      "geometry_id": "TXT::047",
      "engineering_object_id": null,
      "engineering_status": "GEOMETRY_ONLY",
      "status": "READY",
      "text": "B18(200X600)",
      "bbox": {
        "min_x": 12132.071,
        "min_y": 8937.765,
        "max_x": 13541.759,
        "max_y": 9129.672
      },
      "layer": "SEC TEXT",
      "rotation": 359.989,
      "height": 150.0,
      "entity_type": "TEXT",
      "ownership": {
        "owner_type": "ENGINEERING_REINFORCEMENT_CONTEXT",
        "owner_id": "ERC::B12",
        "ownership_source": "BEAM_MATCH",
        "ownership_confidence": 1.0
      }
    },
    {
      "geometry_id": "TXT::048",
      "engineering_object_id": null,
      "engineering_status": "GEOMETRY_ONLY",
      "status": "READY",
      "text": "B18(200X600)",
      "bbox": {
        "min_x": 14069.745,
        "min_y": 8944.267,
        "max_x": 15479.433,
        "max_y": 9136.175
      },
      "layer": "SEC TEXT",
      "rotation": 359.989,
      "height": 150.0,
      "entity_type": "TEXT",
      "ownership": {
        "owner_type": "ENGINEERING_REINFORCEMENT_CONTEXT",
        "owner_id": "ERC::B13",
        "ownership_source": "BEAM_MATCH",
        "ownership_confidence": 1.0
      }
    },
    {
      "geometry_id": "TXT::049",
      "engineering_object_id": null,
      "engineering_status": "GEOMETRY_ONLY",
      "status": "READY",
      "text": "2-Y16",
      "bbox": {
        "min_x": 22808.321,
        "min_y": 18814.377,
        "max_x": 23274.3,
        "max_y": 18974.08
      },
      "layer": "-STR-TEXT",
      "rotation": 0.0,
      "height": 125.0,
      "entity_type": "MTEXT",
      "ownership": {
        "owner_type": "ENGINEERING_REINFORCEMENT_CONTEXT",
        "owner_id": "ERC::B3",
        "ownership_source": "BEAM_MATCH",
        "ownership_confidence": 1.0
      }
    },
    {
      "geometry_id": "TXT::050",
      "engineering_object_id": null,
      "engineering_status": "GEOMETRY_ONLY",
      "status": "READY",
      "text": "2-Y16",
      "bbox": {
        "min_x": 23284.759,
        "min_y": 17112.791,
        "max_x": 23566.144,
        "max_y": 17272.495
      },
      "layer": "-STR-TEXT",
      "rotation": 0.0,
      "height": 125.0,
      "entity_type": "MTEXT",
      "ownership": {
        "owner_type": "ENGINEERING_REINFORCEMENT_CONTEXT",
        "owner_id": "ERC::B3",
        "ownership_source": "BEAM_MATCH",
        "ownership_confidence": 1.0
      }
    },
    {
      "geometry_id": "TXT::051",
      "engineering_object_id": null,
      "engineering_status": "GEOMETRY_ONLY",
      "status": "READY",
      "text": "B12(200X600)",
      "bbox": {
        "min_x": 4299.932,
        "min_y": 12751.608,
        "max_x": 5651.4,
        "max_y": 12943.505
      },
      "layer": "SEC TEXT",
      "rotation": 359.989,
      "height": 150.0,
      "entity_type": "TEXT",
      "ownership": {
        "owner_type": "ENGINEERING_REINFORCEMENT_CONTEXT",
        "owner_id": "ERC::B5",
        "ownership_source": "BEAM_MATCH",
        "ownership_confidence": 1.0
      }
    },
    {
      "geometry_id": "TXT::052",
      "engineering_object_id": null,
      "engineering_status": "GEOMETRY_ONLY",
      "status": "READY",
      "text": "2-Y20",
      "bbox": {
        "min_x": 4934.091,
        "min_y": 13657.131,
        "max_x": 5400.07,
        "max_y": 13816.834
      },
      "layer": "-STR-TEXT",
      "rotation": 0.0,
      "height": 125.0,
      "entity_type": "MTEXT",
      "ownership": {
        "owner_type": "ENGINEERING_REINFORCEMENT_CONTEXT",
        "owner_id": "ERC::B5",
        "ownership_source": "BEAM_MATCH",
        "ownership_confidence": 1.0
      }
    },
    {
      "geometry_id": "TXT::053",
      "engineering_object_id": null,
      "engineering_status": "GEOMETRY_ONLY",
      "status": "READY",
      "text": "2-Y16",
      "bbox": {
        "min_x": 4923.281,
        "min_y": 15050.374,
        "max_x": 5389.26,
        "max_y": 15210.077
      },
      "layer": "-STR-TEXT",
      "rotation": 0.0,
      "height": 125.0,
      "entity_type": "MTEXT",
      "ownership": {
        "owner_type": "ENGINEERING_REINFORCEMENT_CONTEXT",
        "owner_id": "ERC::B5",
        "ownership_source": "BEAM_MATCH",
        "ownership_confidence": 1.0
      }
    },
    {
      "geometry_id": "TXT::054",
      "engineering_object_id": null,
      "engineering_status": "GEOMETRY_ONLY",
      "status": "READY",
      "text": "B12(200X600)",
      "bbox": {
        "min_x": 7570.935,
        "min_y": 12773.317,
        "max_x": 8922.404,
        "max_y": 12965.214
      },
      "layer": "SEC TEXT",
      "rotation": 359.989,
      "height": 150.0,
      "entity_type": "TEXT",
      "ownership": {
        "owner_type": "ENGINEERING_REINFORCEMENT_CONTEXT",
        "owner_id": "ERC::B5",
        "ownership_source": "BEAM_MATCH",
        "ownership_confidence": 1.0
      }
    },
    {
      "geometry_id": "TXT::055",
      "engineering_object_id": null,
      "engineering_status": "GEOMETRY_ONLY",
      "status": "READY",
      "text": "2-Y20",
      "bbox": {
        "min_x": 7288.125,
        "min_y": 13657.131,
        "max_x": 7754.103,
        "max_y": 13816.834
      },
      "layer": "-STR-TEXT",
      "rotation": 0.0,
      "height": 125.0,
      "entity_type": "MTEXT",
      "ownership": {
        "owner_type": "ENGINEERING_REINFORCEMENT_CONTEXT",
        "owner_id": "ERC::B5",
        "ownership_source": "BEAM_MATCH",
        "ownership_confidence": 1.0
      }
    },
    {
      "geometry_id": "TXT::056",
      "engineering_object_id": null,
      "engineering_status": "GEOMETRY_ONLY",
      "status": "READY",
      "text": "2-Y16",
      "bbox": {
        "min_x": 7277.315,
        "min_y": 15050.374,
        "max_x": 7743.293,
        "max_y": 15210.077
      },
      "layer": "-STR-TEXT",
      "rotation": 0.0,
      "height": 125.0,
      "entity_type": "MTEXT",
      "ownership": {
        "owner_type": "ENGINEERING_REINFORCEMENT_CONTEXT",
        "owner_id": "ERC::B1",
        "ownership_source": "BEAM_MATCH",
        "ownership_confidence": 1.0
      }
    },
    {
      "geometry_id": "TXT::057",
      "engineering_object_id": null,
      "engineering_status": "GEOMETRY_ONLY",
      "status": "READY",
      "text": "B12(200X600)",
      "bbox": {
        "min_x": 10858.77,
        "min_y": 12751.608,
        "max_x": 12210.238,
        "max_y": 12943.505
      },
      "layer": "SEC TEXT",
      "rotation": 359.989,
      "height": 150.0,
      "entity_type": "TEXT",
      "ownership": {
        "owner_type": "ENGINEERING_REINFORCEMENT_CONTEXT",
        "owner_id": "ERC::B6",
        "ownership_source": "BEAM_MATCH",
        "ownership_confidence": 1.0
      }
    },
    {
      "geometry_id": "TXT::058",
      "engineering_object_id": null,
      "engineering_status": "GEOMETRY_ONLY",
      "status": "READY",
      "text": "2-Y20",
      "bbox": {
        "min_x": 10776.922,
        "min_y": 13657.131,
        "max_x": 11242.901,
        "max_y": 13816.834
      },
      "layer": "-STR-TEXT",
      "rotation": 0.0,
      "height": 125.0,
      "entity_type": "MTEXT",
      "ownership": {
        "owner_type": "ENGINEERING_REINFORCEMENT_CONTEXT",
        "owner_id": "ERC::B6",
        "ownership_source": "BEAM_MATCH",
        "ownership_confidence": 1.0
      }
    },
    {
      "geometry_id": "TXT::059",
      "engineering_object_id": null,
      "engineering_status": "GEOMETRY_ONLY",
      "status": "READY",
      "text": "2-Y16",
      "bbox": {
        "min_x": 10766.112,
        "min_y": 15050.374,
        "max_x": 11232.091,
        "max_y": 15210.077
      },
      "layer": "-STR-TEXT",
      "rotation": 0.0,
      "height": 125.0,
      "entity_type": "MTEXT",
      "ownership": {
        "owner_type": "ENGINEERING_REINFORCEMENT_CONTEXT",
        "owner_id": "ERC::B1",
        "ownership_source": "BEAM_MATCH",
        "ownership_confidence": 1.0
      }
    },
    {
      "geometry_id": "TXT::060",
      "engineering_object_id": null,
      "engineering_status": "GEOMETRY_ONLY",
      "status": "READY",
      "text": "B13(200X600)",
      "bbox": {
        "min_x": 14368.402,
        "min_y": 12751.608,
        "max_x": 15719.87,
        "max_y": 12943.505
      },
      "layer": "SEC TEXT",
      "rotation": 359.989,
      "height": 150.0,
      "entity_type": "TEXT",
      "ownership": {
        "owner_type": "ENGINEERING_REINFORCEMENT_CONTEXT",
        "owner_id": "ERC::B7",
        "ownership_source": "BEAM_MATCH",
        "ownership_confidence": 1.0
      }
    },
    {
      "geometry_id": "TXT::061",
      "engineering_object_id": null,
      "engineering_status": "GEOMETRY_ONLY",
      "status": "READY",
      "text": "2-Y20",
      "bbox": {
        "min_x": 14977.736,
        "min_y": 13657.131,
        "max_x": 15443.715,
        "max_y": 13816.834
      },
      "layer": "-STR-TEXT",
      "rotation": 0.0,
      "height": 125.0,
      "entity_type": "MTEXT",
      "ownership": {
        "owner_type": "ENGINEERING_REINFORCEMENT_CONTEXT",
        "owner_id": "ERC::B7",
        "ownership_source": "BEAM_MATCH",
        "ownership_confidence": 1.0
      }
    },
    {
      "geometry_id": "TXT::062",
      "engineering_object_id": null,
      "engineering_status": "GEOMETRY_ONLY",
      "status": "READY",
      "text": "2-Y16",
      "bbox": {
        "min_x": 14966.926,
        "min_y": 15050.374,
        "max_x": 15432.905,
        "max_y": 15210.077
      },
      "layer": "-STR-TEXT",
      "rotation": 0.0,
      "height": 125.0,
      "entity_type": "MTEXT",
      "ownership": {
        "owner_type": "ENGINEERING_REINFORCEMENT_CONTEXT",
        "owner_id": "ERC::B7",
        "ownership_source": "BEAM_MATCH",
        "ownership_confidence": 1.0
      }
    },
    {
      "geometry_id": "TXT::063",
      "engineering_object_id": null,
      "engineering_status": "GEOMETRY_ONLY",
      "status": "READY",
      "text": "B13(200X600)",
      "bbox": {
        "min_x": 17659.088,
        "min_y": 12773.317,
        "max_x": 19010.556,
        "max_y": 12965.214
      },
      "layer": "SEC TEXT",
      "rotation": 359.989,
      "height": 150.0,
      "entity_type": "TEXT",
      "ownership": {
        "owner_type": "ENGINEERING_REINFORCEMENT_CONTEXT",
        "owner_id": "ERC::B7",
        "ownership_source": "BEAM_MATCH",
        "ownership_confidence": 1.0
      }
    },
    {
      "geometry_id": "TXT::064",
      "engineering_object_id": null,
      "engineering_status": "GEOMETRY_ONLY",
      "status": "READY",
      "text": "2-Y20",
      "bbox": {
        "min_x": 17331.77,
        "min_y": 13657.131,
        "max_x": 17797.749,
        "max_y": 13816.834
      },
      "layer": "-STR-TEXT",
      "rotation": 0.0,
      "height": 125.0,
      "entity_type": "MTEXT",
      "ownership": {
        "owner_type": "ENGINEERING_REINFORCEMENT_CONTEXT",
        "owner_id": "ERC::B7",
        "ownership_source": "BEAM_MATCH",
        "ownership_confidence": 1.0
      }
    },
    {
      "geometry_id": "TXT::065",
      "engineering_object_id": null,
      "engineering_status": "GEOMETRY_ONLY",
      "status": "READY",
      "text": "2-Y16",
      "bbox": {
        "min_x": 17320.96,
        "min_y": 15050.374,
        "max_x": 17786.939,
        "max_y": 15210.077
      },
      "layer": "-STR-TEXT",
      "rotation": 0.0,
      "height": 125.0,
      "entity_type": "MTEXT",
      "ownership": {
        "owner_type": "ENGINEERING_REINFORCEMENT_CONTEXT",
        "owner_id": "ERC::B7",
        "ownership_source": "BEAM_MATCH",
        "ownership_confidence": 1.0
      }
    },
    {
      "geometry_id": "TXT::066",
      "engineering_object_id": null,
      "engineering_status": "GEOMETRY_ONLY",
      "status": "READY",
      "text": "B13(200X600)",
      "bbox": {
        "min_x": 20923.986,
        "min_y": 12751.608,
        "max_x": 22275.454,
        "max_y": 12943.505
      },
      "layer": "SEC TEXT",
      "rotation": 359.989,
      "height": 150.0,
      "entity_type": "TEXT",
      "ownership": {
        "owner_type": "ENGINEERING_REINFORCEMENT_CONTEXT",
        "owner_id": "ERC::B8",
        "ownership_source": "BEAM_MATCH",
        "ownership_confidence": 1.0
      }
    },
    {
      "geometry_id": "TXT::067",
      "engineering_object_id": null,
      "engineering_status": "GEOMETRY_ONLY",
      "status": "READY",
      "text": "2-Y20",
      "bbox": {
        "min_x": 20820.568,
        "min_y": 13657.131,
        "max_x": 21286.547,
        "max_y": 13816.834
      },
      "layer": "-STR-TEXT",
      "rotation": 0.0,
      "height": 125.0,
      "entity_type": "MTEXT",
      "ownership": {
        "owner_type": "ENGINEERING_REINFORCEMENT_CONTEXT",
        "owner_id": "ERC::B8",
        "ownership_source": "BEAM_MATCH",
        "ownership_confidence": 1.0
      }
    },
    {
      "geometry_id": "TXT::068",
      "engineering_object_id": null,
      "engineering_status": "GEOMETRY_ONLY",
      "status": "READY",
      "text": "2-Y16",
      "bbox": {
        "min_x": 20809.758,
        "min_y": 15050.374,
        "max_x": 21275.737,
        "max_y": 15210.077
      },
      "layer": "-STR-TEXT",
      "rotation": 0.0,
      "height": 125.0,
      "entity_type": "MTEXT",
      "ownership": {
        "owner_type": "ENGINEERING_REINFORCEMENT_CONTEXT",
        "owner_id": "ERC::B8",
        "ownership_source": "BEAM_MATCH",
        "ownership_confidence": 1.0
      }
    },
    {
      "geometry_id": "TXT::069",
      "engineering_object_id": null,
      "engineering_status": "GEOMETRY_ONLY",
      "status": "READY",
      "text": "B14(200X600)",
      "bbox": {
        "min_x": 25458.132,
        "min_y": 12945.968,
        "max_x": 26809.6,
        "max_y": 13137.864
      },
      "layer": "SEC TEXT",
      "rotation": 359.989,
      "height": 150.0,
      "entity_type": "TEXT",
      "ownership": {
        "owner_type": "ENGINEERING_REINFORCEMENT_CONTEXT",
        "owner_id": "ERC::B8",
        "ownership_source": "BEAM_MATCH",
        "ownership_confidence": 1.0
      }
    },
    {
      "geometry_id": "TXT::070",
      "engineering_object_id": null,
      "engineering_status": "GEOMETRY_ONLY",
      "status": "READY",
      "text": "2-Y16",
      "bbox": {
        "min_x": 26249.466,
        "min_y": 14021.424,
        "max_x": 26530.852,
        "max_y": 14181.127
      },
      "layer": "-STR-TEXT",
      "rotation": 0.0,
      "height": 125.0,
      "entity_type": "MTEXT",
      "ownership": {
        "owner_type": "ENGINEERING_REINFORCEMENT_CONTEXT",
        "owner_id": "ERC::B8",
        "ownership_source": "BEAM_MATCH",
        "ownership_confidence": 1.0
      }
    },
    {
      "geometry_id": "TXT::071",
      "engineering_object_id": null,
      "engineering_status": "GEOMETRY_ONLY",
      "status": "READY",
      "text": "2-Y16",
      "bbox": {
        "min_x": 26251.199,
        "min_y": 15099.494,
        "max_x": 26717.178,
        "max_y": 15259.197
      },
      "layer": "-STR-TEXT",
      "rotation": 0.0,
      "height": 125.0,
      "entity_type": "MTEXT",
      "ownership": {
        "owner_type": "ENGINEERING_REINFORCEMENT_CONTEXT",
        "owner_id": "ERC::B3",
        "ownership_source": "BEAM_MATCH",
        "ownership_confidence": 1.0
      }
    },
    {
      "geometry_id": "TXT::072",
      "engineering_object_id": null,
      "engineering_status": "GEOMETRY_ONLY",
      "status": "READY",
      "text": "2-Y16",
      "bbox": {
        "min_x": 25982.352,
        "min_y": 15465.03,
        "max_x": 26448.331,
        "max_y": 15624.733
      },
      "layer": "-STR-TEXT",
      "rotation": 0.0,
      "height": 125.0,
      "entity_type": "MTEXT",
      "ownership": {
        "owner_type": "ENGINEERING_REINFORCEMENT_CONTEXT",
        "owner_id": "ERC::B3",
        "ownership_source": "BEAM_MATCH",
        "ownership_confidence": 1.0
      }
    },
    {
      "geometry_id": "TXT::073",
      "engineering_object_id": null,
      "engineering_status": "GEOMETRY_ONLY",
      "status": "READY",
      "text": "2-Y16",
      "bbox": {
        "min_x": 25799.022,
        "min_y": 13728.409,
        "max_x": 26265.001,
        "max_y": 13888.113
      },
      "layer": "-STR-TEXT",
      "rotation": 0.0,
      "height": 125.0,
      "entity_type": "MTEXT",
      "ownership": {
        "owner_type": "ENGINEERING_REINFORCEMENT_CONTEXT",
        "owner_id": "ERC::B8",
        "ownership_source": "BEAM_MATCH",
        "ownership_confidence": 1.0
      }
    },
    {
      "geometry_id": "TXT::074",
      "engineering_object_id": null,
      "engineering_status": "GEOMETRY_ONLY",
      "status": "READY",
      "text": "B15(200X600)",
      "bbox": {
        "min_x": 30642.886,
        "min_y": 12802.027,
        "max_x": 31994.354,
        "max_y": 12993.924
      },
      "layer": "SEC TEXT",
      "rotation": 359.989,
      "height": 150.0,
      "entity_type": "TEXT",
      "ownership": {
        "owner_type": "ENGINEERING_REINFORCEMENT_CONTEXT",
        "owner_id": "ERC::B11",
        "ownership_source": "BEAM_MATCH",
        "ownership_confidence": 1.0
      }
    },
    {
      "geometry_id": "TXT::075",
      "engineering_object_id": null,
      "engineering_status": "GEOMETRY_ONLY",
      "status": "READY",
      "text": "2-Y16",
      "bbox": {
        "min_x": 30561.038,
        "min_y": 13707.55,
        "max_x": 31027.017,
        "max_y": 13867.253
      },
      "layer": "-STR-TEXT",
      "rotation": 0.0,
      "height": 125.0,
      "entity_type": "MTEXT",
      "ownership": {
        "owner_type": "ENGINEERING_REINFORCEMENT_CONTEXT",
        "owner_id": "ERC::B8",
        "ownership_source": "BEAM_MATCH",
        "ownership_confidence": 1.0
      }
    },
    {
      "geometry_id": "TXT::076",
      "engineering_object_id": null,
      "engineering_status": "GEOMETRY_ONLY",
      "status": "READY",
      "text": "2-Y16",
      "bbox": {
        "min_x": 30550.228,
        "min_y": 15100.793,
        "max_x": 31016.207,
        "max_y": 15260.496
      },
      "layer": "-STR-TEXT",
      "rotation": 0.0,
      "height": 125.0,
      "entity_type": "MTEXT",
      "ownership": {
        "owner_type": "ENGINEERING_REINFORCEMENT_CONTEXT",
        "owner_id": "ERC::B8",
        "ownership_source": "BEAM_MATCH",
        "ownership_confidence": 1.0
      }
    },
    {
      "geometry_id": "TXT::077",
      "engineering_object_id": null,
      "engineering_status": "GEOMETRY_ONLY",
      "status": "READY",
      "text": "2-Y20",
      "bbox": {
        "min_x": 14535.414,
        "min_y": 10074.881,
        "max_x": 15365.376,
        "max_y": 10234.584
      },
      "layer": "-STR-TEXT",
      "rotation": 0.0,
      "height": 125.0,
      "entity_type": "MTEXT",
      "ownership": {
        "owner_type": "ENGINEERING_REINFORCEMENT_CONTEXT",
        "owner_id": "ERC::B13",
        "ownership_source": "BEAM_MATCH",
        "ownership_confidence": 1.0
      }
    },
    {
      "geometry_id": "TXT::078",
      "engineering_object_id": null,
      "engineering_status": "GEOMETRY_ONLY",
      "status": "READY",
      "text": "2-Y20",
      "bbox": {
        "min_x": 14721.31,
        "min_y": 11311.999,
        "max_x": 15187.289,
        "max_y": 11471.702
      },
      "layer": "-STR-TEXT",
      "rotation": 0.0,
      "height": 125.0,
      "entity_type": "MTEXT",
      "ownership": {
        "owner_type": "ENGINEERING_REINFORCEMENT_CONTEXT",
        "owner_id": "ERC::B13",
        "ownership_source": "BEAM_MATCH",
        "ownership_confidence": 1.0
      }
    },
    {
      "geometry_id": "TXT::079",
      "engineering_object_id": null,
      "engineering_status": "GEOMETRY_ONLY",
      "status": "READY",
      "text": "S.F.R.\nON BOTH FACE",
      "bbox": {
        "min_x": 18895.391,
        "min_y": 9159.142,
        "max_x": 19390.19,
        "max_y": 9945.095
      },
      "layer": "-STR-TEXT",
      "rotation": 0.0,
      "height": 125.0,
      "entity_type": "MTEXT",
      "ownership": {
        "owner_type": "ENGINEERING_REINFORCEMENT_CONTEXT",
        "owner_id": "ERC::B13",
        "ownership_source": "BEAM_MATCH",
        "ownership_confidence": 1.0
      }
    },
    {
      "geometry_id": "TXT::080",
      "engineering_object_id": null,
      "engineering_status": "GEOMETRY_ONLY",
      "status": "READY",
      "text": "SIDE.FACE.REINFORCEMENT DETAILS FOR CURVED BEAMS DEPTH>450",
      "bbox": {
        "min_x": 16679.936,
        "min_y": 9208.505,
        "max_x": 24137.781,
        "max_y": 9400.149
      },
      "layer": "-S-BMNO",
      "rotation": 0.0,
      "height": 150.0,
      "entity_type": "TEXT",
      "ownership": {
        "owner_type": "ENGINEERING_REINFORCEMENT_CONTEXT",
        "owner_id": "ERC::B13",
        "ownership_source": "BEAM_MATCH",
        "ownership_confidence": 1.0
      }
    },
    {
      "geometry_id": "TXT::081",
      "engineering_object_id": null,
      "engineering_status": "GEOMETRY_ONLY",
      "status": "READY",
      "text": "S.F.R.- 2-Y10",
      "bbox": {
        "min_x": 18736.254,
        "min_y": 8816.104,
        "max_x": 22155.584,
        "max_y": 9007.748
      },
      "layer": "-S-BMNO",
      "rotation": 0.0,
      "height": 150.0,
      "entity_type": "MTEXT",
      "ownership": {
        "owner_type": "ENGINEERING_REINFORCEMENT_CONTEXT",
        "owner_id": "ERC::B13",
        "ownership_source": "BEAM_MATCH",
        "ownership_confidence": 1.0
      }
    },
    {
      "geometry_id": "TXT::082",
      "engineering_object_id": null,
      "engineering_status": "GEOMETRY_ONLY",
      "status": "READY",
      "text": "B5(200X600)",
      "bbox": {
        "min_x": 5320.374,
        "min_y": 16373.113,
        "max_x": 6613.521,
        "max_y": 16564.999
      },
      "layer": "SEC TEXT",
      "rotation": 359.989,
      "height": 150.0,
      "entity_type": "TEXT",
      "ownership": {
        "owner_type": "ENGINEERING_REINFORCEMENT_CONTEXT",
        "owner_id": "ERC::B1",
        "ownership_source": "BEAM_MATCH",
        "ownership_confidence": 1.0
      }
    },
    {
      "geometry_id": "TXT::083",
      "engineering_object_id": null,
      "engineering_status": "GEOMETRY_ONLY",
      "status": "READY",
      "text": "2-Y20",
      "bbox": {
        "min_x": 2967.959,
        "min_y": 17310.479,
        "max_x": 3249.345,
        "max_y": 17470.182
      },
      "layer": "-STR-TEXT",
      "rotation": 0.0,
      "height": 125.0,
      "entity_type": "MTEXT",
      "ownership": {
        "owner_type": "ENGINEERING_REINFORCEMENT_CONTEXT",
        "owner_id": "ERC::B5",
        "ownership_source": "BEAM_MATCH",
        "ownership_confidence": 1.0
      }
    },
    {
      "geometry_id": "TXT::084",
      "engineering_object_id": null,
      "engineering_status": "GEOMETRY_ONLY",
      "status": "READY",
      "text": "2-Y16",
      "bbox": {
        "min_x": 3825.169,
        "min_y": 18538.549,
        "max_x": 4291.148,
        "max_y": 18698.252
      },
      "layer": "-STR-TEXT",
      "rotation": 0.0,
      "height": 125.0,
      "entity_type": "MTEXT",
      "ownership": {
        "owner_type": "ENGINEERING_REINFORCEMENT_CONTEXT",
        "owner_id": "ERC::B8",
        "ownership_source": "BEAM_MATCH",
        "ownership_confidence": 1.0
      }
    },
    {
      "geometry_id": "TXT::085",
      "engineering_object_id": null,
      "engineering_status": "GEOMETRY_ONLY",
      "status": "READY",
      "text": "2-Y16",
      "bbox": {
        "min_x": 5895.942,
        "min_y": 17162.833,
        "max_x": 6173.218,
        "max_y": 17322.536
      },
      "layer": "-STR-TEXT",
      "rotation": 0.0,
      "height": 125.0,
      "entity_type": "MTEXT",
      "ownership": {
        "owner_type": "ENGINEERING_REINFORCEMENT_CONTEXT",
        "owner_id": "ERC::B1",
        "ownership_source": "BEAM_MATCH",
        "ownership_confidence": 1.0
      }
    },
    {
      "geometry_id": "TXT::086",
      "engineering_object_id": null,
      "engineering_status": "GEOMETRY_ONLY",
      "status": "READY",
      "text": "2-Y12",
      "bbox": {
        "min_x": 7162.61,
        "min_y": 18919.095,
        "max_x": 7628.589,
        "max_y": 19078.798
      },
      "layer": "-STR-TEXT",
      "rotation": 0.0,
      "height": 125.0,
      "entity_type": "MTEXT",
      "ownership": {
        "owner_type": "ENGINEERING_REINFORCEMENT_CONTEXT",
        "owner_id": "ERC::B1",
        "ownership_source": "BEAM_MATCH",
        "ownership_confidence": 1.0
      }
    },
    {
      "geometry_id": "TXT::087",
      "engineering_object_id": null,
      "engineering_status": "GEOMETRY_ONLY",
      "status": "READY",
      "text": "4-Y8,  SIDE FACE REINF. ON BOTH FACES\n(2-Y8 ON ONE FACE)",
      "bbox": {
        "min_x": 6267.218,
        "min_y": 22256.036,
        "max_x": 8892.873,
        "max_y": 22833.24
      },
      "layer": "-STR-TEXT",
      "rotation": 0.0,
      "height": 125.0,
      "entity_type": "MTEXT",
      "ownership": {
        "owner_type": "ENGINEERING_REINFORCEMENT_CONTEXT",
        "owner_id": "ERC::B8",
        "ownership_source": "BEAM_MATCH",
        "ownership_confidence": 1.0
      }
    },
    {
      "geometry_id": "TXT::088",
      "engineering_object_id": null,
      "engineering_status": "GEOMETRY_ONLY",
      "status": "READY",
      "text": "4-Y8,  SIDE FACE REINF. ON BOTH FACES\n(2-Y8 ON ONE FACE)",
      "bbox": {
        "min_x": 24738.113,
        "min_y": 18860.77,
        "max_x": 27363.768,
        "max_y": 19437.973
      },
      "layer": "-STR-TEXT",
      "rotation": 0.0,
      "height": 125.0,
      "entity_type": "MTEXT",
      "ownership": {
        "owner_type": "ENGINEERING_REINFORCEMENT_CONTEXT",
        "owner_id": "ERC::B3",
        "ownership_source": "BEAM_MATCH",
        "ownership_confidence": 1.0
      }
    },
    {
      "geometry_id": "TXT::089",
      "engineering_object_id": null,
      "engineering_status": "GEOMETRY_ONLY",
      "status": "READY",
      "text": "4-Y8,  SIDE FACE REINF. ON BOTH FACES\n(2-Y8 ON ONE FACE)",
      "bbox": {
        "min_x": 27355.578,
        "min_y": 15173.907,
        "max_x": 29981.233,
        "max_y": 15751.11
      },
      "layer": "-STR-TEXT",
      "rotation": 0.0,
      "height": 125.0,
      "entity_type": "MTEXT",
      "ownership": {
        "owner_type": "ENGINEERING_REINFORCEMENT_CONTEXT",
        "owner_id": "ERC::B4",
        "ownership_source": "BEAM_MATCH",
        "ownership_confidence": 1.0
      }
    },
    {
      "geometry_id": "TXT::090",
      "engineering_object_id": null,
      "engineering_status": "GEOMETRY_ONLY",
      "status": "READY",
      "text": "SHR & OHT LVL TOP BEAM REINFORCEMENT GFC DETAILS",
      "bbox": {
        "min_x": 13546.903,
        "min_y": 4135.882,
        "max_x": 21459.536,
        "max_y": 5945.321
      },
      "layer": "G-ANNO-TEXT",
      "rotation": 0.0,
      "height": 400.0,
      "entity_type": "MTEXT",
      "ownership": {
        "owner_type": "ENGINEERING_REINFORCEMENT_CONTEXT",
        "owner_id": "ERC::B8",
        "ownership_source": "BEAM_MATCH",
        "ownership_confidence": 1.0
      }
    },
    {
      "geometry_id": "TXT::091",
      "engineering_object_id": null,
      "engineering_status": "GEOMETRY_ONLY",
      "status": "READY",
      "text": "TYPICAL STIRRUP DETAILS",
      "bbox": {
        "min_x": 28861.224,
        "min_y": 2870.037,
        "max_x": 31702.424,
        "max_y": 3061.681
      },
      "layer": "-S-BMNO",
      "rotation": 0.0,
      "height": 150.0,
      "entity_type": "TEXT",
      "ownership": {
        "owner_type": "ENGINEERING_REINFORCEMENT_CONTEXT",
        "owner_id": "ERC::B8",
        "ownership_source": "BEAM_MATCH",
        "ownership_confidence": 1.0
      }
    }
  ]
}